odoo/addons/mail_notification_custom_subject/README.rst
odoo/addons/mail_notification_custom_subject/__init__.py
odoo/addons/mail_notification_custom_subject/__manifest__.py
odoo/addons/mail_notification_custom_subject/i18n/es.po
odoo/addons/mail_notification_custom_subject/i18n/it.po
odoo/addons/mail_notification_custom_subject/i18n/mail_notification_custom_subject.pot
odoo/addons/mail_notification_custom_subject/models/__init__.py
odoo/addons/mail_notification_custom_subject/models/mail_message_custom_subject.py
odoo/addons/mail_notification_custom_subject/models/mail_thread.py
odoo/addons/mail_notification_custom_subject/readme/CONFIGURE.md
odoo/addons/mail_notification_custom_subject/readme/CONTRIBUTORS.md
odoo/addons/mail_notification_custom_subject/readme/DESCRIPTION.md
odoo/addons/mail_notification_custom_subject/readme/USAGE.md
odoo/addons/mail_notification_custom_subject/security/ir.model.access.csv
odoo/addons/mail_notification_custom_subject/static/description/icon.png
odoo/addons/mail_notification_custom_subject/static/description/index.html
odoo/addons/mail_notification_custom_subject/tests/__init__.py
odoo/addons/mail_notification_custom_subject/tests/test_mail_notification_custom_subject.py
odoo/addons/mail_notification_custom_subject/views/mail_notification_custom_subject_views.xml
odoo_addon_mail_notification_custom_subject-18.0.1.0.0.2.dist-info/METADATA
odoo_addon_mail_notification_custom_subject-18.0.1.0.0.2.dist-info/WHEEL
odoo_addon_mail_notification_custom_subject-18.0.1.0.0.2.dist-info/top_level.txt
odoo_addon_mail_notification_custom_subject-18.0.1.0.0.2.dist-info/RECORD
